[
  {
    "id": 0,
    "date": 1646908327570,
    "duration": "21 мин",
    "participants": 8,
    "participantsList": [
      {
        "name": "alex",
        "id": 0
      },
      {
        "name": "nastya",
        "id": 1
      },
      {
        "name": "denis",
        "id": 2
      },
      {
        "name": "danya",
        "id": 3
      },
      {
        "name": "liza",
        "id": 4
      },
      {
        "name": "valera",
        "id": 5
      },
      {
        "name": "vanya",
        "id": 6
      }
    ]
  },
  {
    "id": 1,
    "date": 1646907327570,
    "duration": "1ч.",
    "participants": 7,
    "participantsList": [
      {
        "name": "alex",
        "id": 0
      },
      {
        "name": "nastya",
        "id": 1
      },
      {
        "name": "denis",
        "id": 2
      },
      {
        "name": "danya",
        "id": 3
      },
      {
        "name": "liza",
        "id": 4
      },
      {
        "name": "valera",
        "id": 5
      },
      {
        "name": "vanya",
        "id": 6
      }
    ]
  },
  {
    "id": 2,
    "date": 1646906327570,
    "duration": "1ч. 2 мин",
    "participants": 9,
    "participantsList": [
      {
        "name": "alex",
        "id": 0
      },
      {
        "name": "nastya",
        "id": 1
      },
      {
        "name": "denis",
        "id": 2
      },
      {
        "name": "danya",
        "id": 3
      },
      {
        "name": "liza",
        "id": 4
      },
      {
        "name": "valera",
        "id": 5
      },
      {
        "name": "vanya",
        "id": 6
      }
    ]
  },
  {
    "id": 3,
    "date": 1646905327570,
    "duration": "1ч. 29 мин",
    "participants": 3,
    "participantsList": [
      {
        "name": "alex",
        "id": 0
      },
      {
        "name": "denis",
        "id": 2
      }
    ]
  },
  {
    "id": 4,
    "date": 1646904327570,
    "duration": "1ч. 22 мин",
    "participants": 5,
    "participantsList": [
      {
        "name": "denis",
        "id": 2
      },
      {
        "name": "danya",
        "id": 3
      },
      {
        "name": "liza",
        "id": 4
      },
      {
        "name": "valera",
        "id": 5
      },
      {
        "name": "vanya",
        "id": 6
      }
    ]
  },
  {
    "id": 5,
    "date": 1646903327570,
    "duration": "42 мин",
    "participants": 4,
    "participantsList": [
      {
        "name": "alex",
        "id": 0
      },
      {
        "name": "nastya",
        "id": 1
      }
    ]
  }
]
